appname_generator/__init__.py
appname_generator/__main__.py
appname_generator/generator/__init__.py
appname_generator/generator/availability.py
appname_generator/generator/dictionary.py
appname_generator/generator/generator.py
appname_generator/generator/nouns.py
appname_generator/generator/utils.py
appname_generator-0.1.1.dist-info/METADATA
appname_generator-0.1.1.dist-info/WHEEL
appname_generator-0.1.1.dist-info/entry_points.txt
appname_generator-0.1.1.dist-info/top_level.txt
appname_generator-0.1.1.dist-info/RECORD
